nico_font_tool/__init__.py
nico_font_tool/bdf.py
nico_font_tool/font.py
nico_font_tool/nicofont.py
nico_font_tool/opentype.py
nico_font_tool-0.0.6.dist-info/LICENSE
nico_font_tool-0.0.6.dist-info/METADATA
nico_font_tool-0.0.6.dist-info/WHEEL
nico_font_tool-0.0.6.dist-info/entry_points.txt
nico_font_tool-0.0.6.dist-info/top_level.txt
nico_font_tool-0.0.6.dist-info/RECORD
