Metadata-Version: 2.1
Name: nico-font-tool
Version: 0.0.6
Summary: A tool for converting fonts to NICO Game Framework format fonts.
Author: TakWolf
Maintainer: TakWolf
License: MIT License
Project-URL: homepage, https://github.com/TakWolf/nico-font-tool.python
Project-URL: source, https://github.com/TakWolf/nico-font-tool.python
Project-URL: issues, https://github.com/TakWolf/nico-font-tool.python/issues
Keywords: nico,game-engine,font
Classifier: Programming Language :: Python :: 3
Classifier: License :: OSI Approved :: MIT License
Classifier: Operating System :: OS Independent
Requires-Python: >=3.11
License-File: LICENSE
Requires-Dist: fonttools (>=4.39.4)
Requires-Dist: Brotli (>=1.0.9)
Requires-Dist: bdffont (>=0.0.10)
Requires-Dist: Pillow (>=9.5.0)
Requires-Dist: pypng (>=0.20220715.0)
